{
  "unversionedId": "components/feedback/index",
  "id": "components/feedback/index",
  "isDocsHomePage": false,
  "title": "Getting Started",
  "description": "Installation",
  "source": "@site/docs/components/feedback/index.md",
  "slug": "/components/feedback/index",
  "permalink": "/components/feedback/index",
  "editUrl": "https://github.com/avaiity/availity-react/edit/master/docs/components/feedback/index.md",
  "version": "current",
  "sidebar": "someSidebar",
  "previous": {
    "title": "Feature",
    "permalink": "/components/feature"
  },
  "next": {
    "title": "<Feedback /> ( Default Export )",
    "permalink": "/components/feedback/feedback"
  }
}